lgplibdemo/__init__.py
lgplibdemo/lgpdemo.py
lgplibdemo/lgplib.py
twine2/__init__.py
twine2/__main__.py
twine2/_installed.py
twine2/auth.py
twine2/cli.py
twine2/exceptions.py
twine2/hello.py
twine2/package.py
twine2/repository.py
twine2/settings.py
twine2/utils.py
twine2/wheel.py
twine2/commands/__init__.py
twine2/commands/upload.py
lyptest1-0.0.42.dist-info/METADATA
lyptest1-0.0.42.dist-info/WHEEL
lyptest1-0.0.42.dist-info/entry_points.txt
lyptest1-0.0.42.dist-info/top_level.txt
lyptest1-0.0.42.dist-info/RECORD
