Metadata-Version: 2.1
Name: lyptest1
Version: 0.0.42
Summary: python 3.7-->3.6 
Home-page: https://github.com/ligaopan/lgp-library
Author: pylyp456
Author-email: 25506871@qq.com
License: MIT Licence
Keywords: testing testautomation
Platform: any
Requires-Python: >=3.6.*
